htmresearch/__init__.py
htmresearch/algorithms/TM.py
htmresearch/algorithms/__init__.py
htmresearch/algorithms/apical_dependent_temporal_memory.py
htmresearch/algorithms/apical_tiebreak_temporal_memory.py
htmresearch/algorithms/column_pooler.py
htmresearch/algorithms/faulty_spatial_pooler.py
htmresearch/algorithms/faulty_temporal_memory.py
htmresearch/algorithms/faulty_temporal_memory_shim.py
htmresearch/algorithms/hidden_markov_model.py
htmresearch/algorithms/hierarchical_clustering.py
htmresearch/algorithms/image_sparse_net.py
htmresearch/algorithms/lateral_pooler.py
htmresearch/algorithms/location_modules.py
htmresearch/algorithms/multiconnections.py
htmresearch/algorithms/online_extreme_learning_machine.py
htmresearch/algorithms/simple_union_pooler.py
htmresearch/algorithms/single_layer_location_memory.py
htmresearch/algorithms/sparse_net.py
htmresearch/algorithms/temporal_memory_factory.py
htmresearch/algorithms/temporal_pooler.py
htmresearch/algorithms/union_temporal_pooler.py
htmresearch/data/__init__.py
htmresearch/data/sequence_generator.py
htmresearch/data/sm_sequences.py
htmresearch/frameworks/__init__.py
htmresearch/frameworks/grid_cell_learning/CAN.py
htmresearch/frameworks/grid_cell_learning/__init__.py
htmresearch/frameworks/grid_cell_learning/compute_hardwired_weights.py
htmresearch/frameworks/layers/__init__.py
htmresearch/frameworks/layers/combined_sequence_experiment.py
htmresearch/frameworks/layers/combined_sequence_experiment2.py
htmresearch/frameworks/layers/combined_sequence_network_creation.py
htmresearch/frameworks/layers/combined_sequence_network_creation2.py
htmresearch/frameworks/layers/continuous_location_object_machine.py
htmresearch/frameworks/layers/l2456_model.py
htmresearch/frameworks/layers/l2456_network_creation.py
htmresearch/frameworks/layers/l2_l4_inference.py
htmresearch/frameworks/layers/l2_l4_network_creation.py
htmresearch/frameworks/layers/laminar_network.py
htmresearch-0.0.3.dist-info/DESCRIPTION.rst
htmresearch-0.0.3.dist-info/METADATA
htmresearch-0.0.3.dist-info/RECORD
htmresearch-0.0.3.dist-info/WHEEL
htmresearch-0.0.3.dist-info/metadata.json
htmresearch-0.0.3.dist-info/top_level.txt
